<?xml version="1.0" encoding="UTF-8"?>
<site>
   <feature url="features/com.mecha1.atom.sdk_1.0.0.qualifier.jar" id="com.mecha1.atom.sdk" version="1.0.0.qualifier">
      <category name="atom"/>
   </feature>
   <feature url="features/com.mecha1.atom.mysql.feature_1.0.0.qualifier.jar" id="com.mecha1.atom.mysql.feature" version="1.0.0.qualifier">
      <category name="atom-extensions"/>
   </feature>
   <category-def name="atom" label="Atom">
      <description>
         Language-oriented development tools
      </description>
   </category-def>
   <category-def name="atom-extensions" label="Atom Extensions"/>
</site>
